odoo/addons/sale_portal_debranding/README.rst
odoo/addons/sale_portal_debranding/__init__.py
odoo/addons/sale_portal_debranding/__manifest__.py
odoo/addons/sale_portal_debranding/i18n/de.po
odoo/addons/sale_portal_debranding/i18n/it.po
odoo/addons/sale_portal_debranding/i18n/sale_portal_debranding.pot
odoo/addons/sale_portal_debranding/readme/CONTRIBUTORS.md
odoo/addons/sale_portal_debranding/readme/DESCRIPTION.md
odoo/addons/sale_portal_debranding/static/description/icon.png
odoo/addons/sale_portal_debranding/static/description/index.html
odoo/addons/sale_portal_debranding/static/description/sale_portal_debranding_after.png
odoo/addons/sale_portal_debranding/static/description/sale_portal_debranding_before.png
odoo/addons/sale_portal_debranding/tests/test_sale_portal_debranding.py
odoo/addons/sale_portal_debranding/views/sale_portal_templates.xml
odoo_addon_sale_portal_debranding-19.0.1.0.0.6.dist-info/METADATA
odoo_addon_sale_portal_debranding-19.0.1.0.0.6.dist-info/WHEEL
odoo_addon_sale_portal_debranding-19.0.1.0.0.6.dist-info/top_level.txt
odoo_addon_sale_portal_debranding-19.0.1.0.0.6.dist-info/RECORD
